testservices/__init__.py
testservices/collection.py
testservices/provider.py
testservices/py.typed
testservices/service.py
testservices/supplier.py
testservices/tcp.py
testservices/services/__init__.py
testservices/services/containers.py
testservices/services/databases.py
testservices/services/config/clickhouse/docker_related_config.xml
testservices-0.3.1.dist-info/LICENSE.rst
testservices-0.3.1.dist-info/METADATA
testservices-0.3.1.dist-info/WHEEL
testservices-0.3.1.dist-info/top_level.txt
testservices-0.3.1.dist-info/RECORD
